README.md
setup.cfg
setup.py
easy_openshift/__init__.py
easy_openshift/openshift.py
easy_openshift/openshift_utils.py
easy_openshift.egg-info/PKG-INFO
easy_openshift.egg-info/SOURCES.txt
easy_openshift.egg-info/dependency_links.txt
easy_openshift.egg-info/requires.txt
easy_openshift.egg-info/top_level.txt