Metadata-Version: 1.2
Name: easy-openshift
Version: 0.5.7.2.2
Summary: A python module to interact with openshift API.
Home-page: https://github.com/GoDllkE/python-api-openshift
Author: Gustavo Toledo de Oliveira, Tiago Albuquerque
Author-email: gustavot53@gmail.com, Tiago.gba@hotmail.com
License: UNKNOWN
Download-URL: https://github.com/GoDllkE/Easy-Openshift/archive/master.zip
Project-URL: Source, https://github.com/GoDllkE/python-api-openshift
Project-URL: Documentation, https://github.com/GoDllkE/python-api-openshift/docs
Project-URL: Tracker, https://github.com/GoDllkE/python-api-openshift/issues
Keywords: openshift,origin,easy-openshift,openshift api,python openshift,oc.py
Platform: UNKNOWN
Classifier: Development Status :: 3 - Alpha
Classifier: Intended Audience :: Developers
Classifier: Operating System :: OS Independent
Classifier: License :: OSI Approved :: GNU General Public License v3 (GPLv3)
Classifier: Natural Language :: Portuguese (Brazilian)
Classifier: Programming Language :: Python :: 3
Classifier: Programming Language :: Python :: 3.4
Classifier: Programming Language :: Python :: 3.5
Classifier: Programming Language :: Python :: 3.6
Classifier: Programming Language :: Python :: 3 :: Only
